libOrbbecSDK.1.10.5.dylib
libOrbbecSDK.1.10.dylib
libOrbbecSDK.dylib
pyorbbecsdk.cpython-311-darwin.so
pyorbbecsdk-1.3.1.dist-info/LICENSE
pyorbbecsdk-1.3.1.dist-info/METADATA
pyorbbecsdk-1.3.1.dist-info/WHEEL
pyorbbecsdk-1.3.1.dist-info/top_level.txt
pyorbbecsdk-1.3.1.dist-info/RECORD
