Metadata-Version: 2.1
Name: pyorbbecsdk
Version: 1.3.1
Summary: pyorbbecsdk is a python wrapper for the OrbbecSDK
Author: Joe Dong
Author-email: mocun@orbbec.com
License-File: LICENSE
